usr/share/man/man1/ducker.1
usr/share/info/ducker.info
etc/fish/completions/ducker.fish
etc/bash_completion.d/ducker.bash
ducker-2.0.1.dist-info/entry_points.txt
ducker-2.0.1.dist-info/DESCRIPTION.rst
ducker-2.0.1.dist-info/metadata.json
ducker-2.0.1.dist-info/RECORD
ducker-2.0.1.dist-info/WHEEL
ducker-2.0.1.dist-info/METADATA
ducker-2.0.1.dist-info/top_level.txt
ducker/__init__.py
ducker/ducker.py
