Metadata-Version: 2.0
Name: ducker
Version: 2.0.1
Summary: Program that lets you search with DuckDuckGo from the
Home-page: https://www.freakspot.net/programas/ducker/
Author: Jorge Maldonado Ventura
Author-email: jorgesumle@freakspot.net
License: GNU General Public License v3 (GPLv3)
Keywords: CLI DuckDuckGo search terminal
Platform: UNKNOWN
Classifier: Environment :: Console
Classifier: Intended Audience :: Developers
Classifier: Intended Audience :: End Users/Desktop
Classifier: Intended Audience :: System Administrators
Classifier: License :: OSI Approved :: GNU General Public License v3 (GPLv3)
Classifier: Programming Language :: Python
Classifier: Programming Language :: Python :: 3
Classifier: Programming Language :: Python :: 3.3
Classifier: Programming Language :: Python :: 3.4
Classifier: Programming Language :: Python :: 3.5
Classifier: Programming Language :: Python :: 3.6
Classifier: Topic :: Internet
Classifier: Topic :: Internet :: WWW/HTTP
Classifier: Topic :: Internet :: WWW/HTTP :: Indexing/Search
